.hgignore
.hgtags
AgilentDSO.py
DSO_Vee.txt
ISFWaveform.py
LeCroy.py
MANIFEST
MANIFEST.in
Makefile
PKG-INFO
PMAP.pxd
PMAP.pyx
README.html
README.md
README.rst
README.txt
RebootLanGbib.py
TDS3000Reboot.py
TekDPO.py
TekOSC.py
TekWaveform.py
VXI11.i
VXI11.pyc
VXI11.rpcl
VXI11_intr.rpcl
YokogawaSL1K.py
cPMAP.cpp
cPMAP.h
cVXI11.pxd
cVXI11.pyx
cVXI11_revision.py
createAbtChannel.c
getifaddrs.pxd
getifaddrs.pyx
hgstamp.py
setup.cfg
setup.py
vxi11Device.py
vxi11Exceptions.py
vxi11_device_clear.c
vxi11_scan.c
vxi11_scan.py
vxiLecroy.py
PyVXI11.egg-info/PKG-INFO
PyVXI11.egg-info/SOURCES.txt
PyVXI11.egg-info/dependency_links.txt
PyVXI11.egg-info/top_level.txt