Metadata-Version: 2.1
Name: PyVXI11
Version: 1.15.58
Summary: A Cython based Python module to control devices over VXI11 protocol.
Home-page: http://j-parc.jp/ctrl/documents/
Author: Noboru Yamamoto, KEK, JAPAN
Author-email: Noboru.YAMAMOTO@kek.jp
License: UNKNOWN
Platform: UNKNOWN
Classifier: Programming Language :: Python :: 2.7
Classifier: Programming Language :: Python :: 3
Classifier: Programming Language :: Cython
Classifier: Topic :: Scientific/Engineering :: Interface Engine/Protocol Translator
